advanced_ssh_config/__init__.py
advanced_ssh_config/advanced_ssh_config.py
advanced_ssh_config/bin.py
advanced_ssh_config/config.py
advanced_ssh_config/exceptions.py
advanced_ssh_config/network.py
advanced_ssh_config/ssh_config.py
advanced_ssh_config/utils.py
advanced_ssh_config/tests/__init__.py
advanced_ssh_config/tests/test_advanced_ssh_config.py
advanced_ssh_config/tests/test_bin.py
advanced_ssh_config/tests/test_config.py
advanced_ssh_config/tests/test_utils.py
advanced_ssh_config-1.1.0.dist-info/DESCRIPTION.rst
advanced_ssh_config-1.1.0.dist-info/entry_points.txt
advanced_ssh_config-1.1.0.dist-info/METADATA
advanced_ssh_config-1.1.0.dist-info/metadata.json
advanced_ssh_config-1.1.0.dist-info/RECORD
advanced_ssh_config-1.1.0.dist-info/top_level.txt
advanced_ssh_config-1.1.0.dist-info/WHEEL
