Metadata-Version: 1.0
Name: advanced-ssh-config
Version: 1.1.0
Summary: Add some magic to SSH and .ssh/config
Home-page: https://github.com/moul/advanced-ssh-config
Author: Manfred Touron
Author-email: m@42.am
License: MIT
Download-URL: https://github.com/moul/advanced-ssh-config/archive/master.zip
Platform: UNKNOWN
Classifier: Development Status :: 3 - Alpha
Classifier: Intended Audience :: System Administrators
Classifier: License :: OSI Approved :: MIT License
Classifier: Operating System :: MacOS
Classifier: Operating System :: POSIX
Classifier: Operating System :: Unix
Classifier: Programming Language :: Python
Classifier: Topic :: Internet
Classifier: Topic :: Software Development :: Libraries :: Python Modules
Classifier: Topic :: System :: Shells
Classifier: Topic :: System :: Systems Administration
